easier_data/__init__.py
easier_data/arrays.py
easier_data/data_points.py
easier_data-0.1.5.dist-info/METADATA
easier_data-0.1.5.dist-info/WHEEL
easier_data-0.1.5.dist-info/top_level.txt
easier_data-0.1.5.dist-info/RECORD
