Metadata-Version: 2.4
Name: easier-data
Version: 0.1.5
Summary: Python package for managing data and plotting easier 
Requires-Python: >=3.13
Requires-Dist: ipykernel>=6.29.5
Requires-Dist: jupyter>=1.1.1
Requires-Dist: matplotlib>=3.10.3
Requires-Dist: numpy>=2.2.6
Requires-Dist: pandas>=2.2.3
